setup.py
cqsfsaver/__init__.py
cqsfsaver/cqsfsaver.py
cqsfsaver.egg-info/PKG-INFO
cqsfsaver.egg-info/SOURCES.txt
cqsfsaver.egg-info/dependency_links.txt
cqsfsaver.egg-info/entry_points.txt
cqsfsaver.egg-info/top_level.txt