Metadata-Version: 1.0
Name: cqsfsaver
Version: 0.1.1
Summary: Cqstyle file saver
Home-page: UNKNOWN
Author: Vitaly
Author-email: ps.axjf@gmail.com
License: UNKNOWN
Platform: UNKNOWN
